sqlite/__init__.py
sqlite/__main__.py
sqlite/db.py
Surfy.SQLite-1.0.0.dist-info/METADATA
Surfy.SQLite-1.0.0.dist-info/WHEEL
Surfy.SQLite-1.0.0.dist-info/top_level.txt
Surfy.SQLite-1.0.0.dist-info/RECORD
