Metadata-Version: 2.1
Name: Surfy.SQLite
Version: 1.0.0
Author: Alexander Yermolenko
Project-URL: Homepage, https://surfy.one
Project-URL: GitHub, https://github.com/theastroscout/SQLite.py
Project-URL: Bug Tracker, https://github.com/hqdaemon/SQLite.py/issues
Classifier: Programming Language :: Python :: 3
Classifier: License :: OSI Approved :: MIT License
Classifier: Operating System :: OS Independent
Requires-Python: >=3.7
